{
  "schemaVersion": 1,
  "id": "lightsaber",
  "version": "${version}",

  "name": "SurvivalPlus Lightsabers",
  "description": "This is an official add-on for SurvivalPlus that adds Lightsabers!",
  "authors": [
    "coolsim"
  ],
  "contact": {
    "homepage": "https://www.curseforge.com/minecraft/mc-mods/survivalplus-lightsabers-fabric",
    "sources": "http://github.com/coolsimulations/survivalplus-lightsabers/",
    "issues": "http://github.com/coolsimulations/survivalplus-lightsabers/issues/"
  },

  "license": "All Rights Reserved",
  "icon": "logo.png",

  "environment": "*",
  "entrypoints": {
    "main": [
      "net.coolsimulations.Lightsaber.Lightsaber"
    ],
    "client": [
      "net.coolsimulations.Lightsaber.LightsaberClient"
    ],
    "modmenu": [
      "net.coolsimulations.Lightsaber.config.LSConfigGUI"
    ],
    "rei_client": [
      "net.coolsimulations.Lightsaber.util.LightsaberREI"
    ],
    "emi": [
      "net.coolsimulations.Lightsaber.util.LightsaberEMI"
    ]
  },
  
  "mixins": [
    "lightsaber.mixins.json"
    ],

  "depends": {
    "fabricloader": ">=0.14.17",
    "fabric": "*",
    "minecraft": "1.19.x",
    "survivalplus": "*"
  },
  "custom": {
    "modupdater": {
      "strategy": "curseforge",
      "projectID": 308372
    },
    "modmenu": {
      "links": {
        "modmenu.discord": "https://discord.gg/7DDsHfQ",
        "modmenu.guilded": "https://guilded.gg/i/Wkn138B2"
      }
    }
  }
}