{
    "__comment": "Model generated using MrCrayfish's Model Creator (http://mrcrayfish.com/modelcreator/)",
    "textures": {
        "0": "ic2:blocks/resource/steel_block",
        "1": "lightsaber:blocks/darksaber"
    },
     "display": {
        "gui": {
            "rotation": [ 0, -10, -40 ],
            "translation": [ -5, -6, 0 ],
            "scale": [ 0.7, 0.7, 0.7 ]
        },
        "fixed": {
            "rotation": [ 0, 180, 0 ],
            "translation": [ 0, -9, 0],
            "scale":[ 0.75, 0.75, 0.75 ]
        }
    },
    "elements": [
        {
            "name": "Handle",
            "from": [ 7.2, 7.0, 6.2 ], 
            "to": [ 8.7, 15.0, 8.7 ], 
            "faces": {
                "north": { "texture": "#0", "uv": [ 0.0, 0.0, 1.5, 8.0 ] },
                "east": { "texture": "#0", "uv": [ 0.0, 4.0, 6.0, 12.0 ] },
                "south": { "texture": "#0", "uv": [ 0.0, 1.0, 1.5, 9.0 ] },
                "west": { "texture": "#0", "uv": [ 1.0, 5.0, 7.0, 13.0 ] },
                "up": { "texture": "#0", "uv": [ 0.0, 0.0, 1.5, 2.5 ] },
                "down": { "texture": "#0", "uv": [ 0.0, 0.0, 1.5, 2.5 ] }
            }
        },
        {
            "name": "Main_Edge1",
            "from": [ 7.0, 13.0, 8.7 ], 
            "to": [ 9.0, 13.5, 9.7 ], 
            "faces": {
                "north": { "texture": "#-1", "uv": [ 0.0, 3.0, 2.0, 2.5 ] },
                "east": { "texture": "#0", "uv": [ 0.0, 13.0, 1.0, 13.5 ] },
                "south": { "texture": "#0", "uv": [ 0.0, 3.0, 2.0, 2.5 ] },
                "west": { "texture": "#0", "uv": [ 0.0, 0.0, 1.0, 0.5 ] },
                "up": { "texture": "#0", "uv": [ 0.0, 6.0, 2.0, 7.0 ] },
                "down": { "texture": "#0", "uv": [ 4.0, 12.0, 6.0, 13.0 ] }
            }
        },
        {
            "name": "Main_Edge2",
            "from": [ 7.0, 13.0, 5.699999999999999 ], 
            "to": [ 9.0, 13.5, 6.199999999999999 ], 
            "faces": {
                "north": { "texture": "#0", "uv": [ 0.0, 6.0, 2.0, 6.5 ] },
                "east": { "texture": "#0", "uv": [ 0.0, 0.0, 0.5, 0.5 ] },
                "south": { "texture": "#-1", "uv": [ 0.0, 6.0, 2.0, 6.5 ] },
                "west": { "texture": "#0", "uv": [ 0.0, 0.0, 4.5, 0.5 ] },
                "up": { "texture": "#0", "uv": [ 7.0, 0.0, 9.0, 0.5 ] },
                "down": { "texture": "#0", "uv": [ 7.0, 0.0, 9.0, 0.5 ] }
            }
        },
        {
            "name": "Main_Edge3",
            "from": [ 7.0, 13.0, 6.2 ], 
            "to": [ 7.2, 13.5, 8.7 ], 
            "faces": {
                "north": { "texture": "#-1", "uv": [ 0.0, 0.0, 0.2, 0.5 ] },
                "east": { "texture": "#-1", "uv": [ 0.0, 0.0, 2.5, 0.5 ] },
                "south": { "texture": "#-1", "uv": [ 0.0, 0.0, 0.2, 0.5 ] },
                "west": { "texture": "#0", "uv": [ 5.0, 5.0, 7.5, 5.5 ] },
                "up": { "texture": "#0", "uv": [ 0.0, 0.0, 0.2, 2.5 ] },
                "down": { "texture": "#0", "uv": [ 0.0, 0.0, 0.2, 2.5 ] }
            }
        },
        {
            "name": "Main_Edge4",
            "from": [ 8.7, 13.0, 6.2 ], 
            "to": [ 9.0, 13.5, 8.7 ], 
            "faces": {
                "north": { "texture": "#-1", "uv": [ 0.0, 0.0, 0.3, 0.5 ] },
                "east": { "texture": "#0", "uv": [ 5.0, 0.0, 7.5, 0.5 ] },
                "south": { "texture": "#-1", "uv": [ 0.0, 0.0, 0.3, 0.5 ] },
                "west": { "texture": "#-1", "uv": [ 0.0, 0.0, 2.5, 0.5 ] },
                "up": { "texture": "#0", "uv": [ 0.0, 0.0, 0.3, 2.5 ] },
                "down": { "texture": "#0", "uv": [ 0.0, 0.0, 0.3, 2.5 ] }
            }
        },
        {
            "name": "Main_Edge5",
            "from": [ 7.0, 13.5, 9.5 ], 
            "to": [ 9.0, 14.5, 9.7 ], 
            "faces": {
                "north": { "texture": "#0", "uv": [ 7.0, 13.0, 9.0, 14.0 ] },
                "east": { "texture": "#0", "uv": [ 1.0, 6.0, 1.2, 7.0 ] },
                "south": { "texture": "#0", "uv": [ 7.0, 13.0, 9.0, 14.0 ] },
                "west": { "texture": "#0", "uv": [ 0.0, 0.0, 0.2, 1.0 ] },
                "up": { "texture": "#0", "uv": [ 2.0, 1.0, 4.0, 1.2 ] },
                "down": { "texture": "#-1", "uv": [ 0.0, 0.0, 2.0, 0.2 ] }
            }
        },
        {
            "name": "Lower_Edge1",
            "from": [ 7.0, 7.199999999999999, 6.5 ], 
            "to": [ 7.2, 8.2, 7.0 ], 
            "faces": {
                "north": { "texture": "#0", "uv": [ 0.0, 0.0, 0.2, 1.0 ] },
                "east": { "texture": "#-1", "uv": [ 0.0, 0.0, 0.5, 1.0 ] },
                "south": { "texture": "#0", "uv": [ 0.0, 0.0, 0.2, 1.0 ] },
                "west": { "texture": "#0", "uv": [ 0.0, 5.0, 0.5, 7.0 ] },
                "up": { "texture": "#0", "uv": [ 0.0, 0.0, 0.2, 0.5 ] },
                "down": { "texture": "#-1", "uv": [ 0.0, 0.0, 0.2, 0.5 ] }
            }
        },
        {
            "name": "Lower_Edge2",
            "from": [ 8.7, 7.199999999999999, 6.5 ], 
            "to": [ 8.899999999999999, 8.2, 7.0 ], 
            "faces": {
                "north": { "texture": "#0", "uv": [ 0.0, 0.0, 0.2, 1.0 ] },
                "east": { "texture": "#0", "uv": [ 0.0, 9.0, 0.5, 11.0 ] },
                "south": { "texture": "#0", "uv": [ 0.0, 0.0, 0.2, 1.0 ] },
                "west": { "texture": "#-1", "uv": [ 0.0, 0.0, 0.5, 1.0 ] },
                "up": { "texture": "#0", "uv": [ 0.0, 0.0, 0.2, 0.5 ] },
                "down": { "texture": "#-1", "uv": [ 0.0, 0.0, 0.2, 0.5 ] }
            }
        },
        {
            "name": "Bottom_Edge1",
            "from": [ 7.0, 7.0, 6.0 ], 
            "to": [ 9.0, 7.2, 6.2 ], 
            "faces": {
                "north": { "texture": "#0", "uv": [ 0.0, 13.0, 2.0, 13.2 ] },
                "east": { "texture": "#0", "uv": [ 0.0, 2.0, 0.2, 2.2 ] },
                "south": { "texture": "#-1", "uv": [ 0.0, 0.0, 2.0, 0.2 ] },
                "west": { "texture": "#0", "uv": [ 0.0, 0.0, 0.2, 0.2 ] },
                "up": { "texture": "#0", "uv": [ 0.0, 6.0, 2.0, 6.2 ] },
                "down": { "texture": "#0", "uv": [ 0.0, 12.0, 2.0, 12.2 ] }
            }
        },
        {
            "name": "Bottom_Edge2",
            "from": [ 7.0, 7.0, 8.7 ], 
            "to": [ 9.0, 7.2, 8.899999999999999 ], 
            "faces": {
                "north": { "texture": "#-1", "uv": [ 0.0, 0.0, 2.0, 0.2 ] },
                "east": { "texture": "#0", "uv": [ 0.0, 0.0, 0.2, 0.2 ] },
                "south": { "texture": "#0", "uv": [ 0.0, 2.0, 2.0, 2.2 ] },
                "west": { "texture": "#0", "uv": [ 0.0, 2.0, 0.2, 2.2 ] },
                "up": { "texture": "#0", "uv": [ 0.0, 2.0, 2.0, 2.2 ] },
                "down": { "texture": "#0", "uv": [ 0.0, 2.0, 2.0, 2.2 ] }
            }
        },
        {
            "name": "Bottom_Edge3",
            "from": [ 8.7, 7.0, 6.199999999999999 ], 
            "to": [ 9.0, 7.2, 8.7 ], 
            "faces": {
                "north": { "texture": "#-1", "uv": [ 0.0, 0.0, 0.3, 0.2 ] },
                "east": { "texture": "#0", "uv": [ 0.0, 6.0, 2.5, 6.2 ] },
                "south": { "texture": "#-1", "uv": [ 0.0, 0.0, 0.3, 0.2 ] },
                "west": { "texture": "#-1", "uv": [ 0.0, 0.0, 2.5, 0.2 ] },
                "up": { "texture": "#0", "uv": [ 0.0, 0.0, 0.3, 2.5 ] },
                "down": { "texture": "#0", "uv": [ 0.0, 0.0, 0.3, 2.5 ] }
            }
        },
        {
            "name": "Bottom_Edge4",
            "from": [ 7.0, 7.0, 6.2 ], 
            "to": [ 7.2, 7.2, 8.7 ], 
            "faces": {
                "north": { "texture": "#-1", "uv": [ 0.0, 0.0, 0.2, 0.2 ] },
                "east": { "texture": "#-1", "uv": [ 0.0, 0.0, 2.5, 0.2 ] },
                "south": { "texture": "#-1", "uv": [ 0.0, 0.0, 0.2, 0.2 ] },
                "west": { "texture": "#0", "uv": [ 0.0, 0.0, 2.5, 0.2 ] },
                "up": { "texture": "#0", "uv": [ 0.0, 0.0, 0.2, 2.5 ] },
                "down": { "texture": "#0", "uv": [ 0.0, 1.0, 0.2, 3.5 ] }
            }
        },
        {
            "name": "Button",
            "from": [ 7.5, 10.0, 8.7 ], 
            "to": [ 8.5, 12.2, 8.899999999999999 ], 
            "faces": {
                "north": { "texture": "#-1", "uv": [ 0.0, 3.0, 4.0, 8.0 ] },
                "east": { "texture": "#1", "uv": [ 0.0, 3.0, 0.2, 5.2 ] },
                "south": { "texture": "#1", "uv": [ 0.0, 3.0, 4.0, 8.0 ] },
                "west": { "texture": "#1", "uv": [ 0.0, 3.0, 0.2, 5.2 ] },
                "up": { "texture": "#1", "uv": [ 0.0, 3.0, 1.0, 3.2 ] },
                "down": { "texture": "#1", "uv": [ 0.0, 3.0, 1.0, 3.2 ] }
            }
        }
    ]
}